MANIFEST.in
setup.cfg
setup.py
versioneer.py
pyfolio/__init__.py
pyfolio/_seaborn.py
pyfolio/_version.py
pyfolio/bayesian.py
pyfolio/capacity.py
pyfolio/deprecate.py
pyfolio/interesting_periods.py
pyfolio/ipycompat.py
pyfolio/perf_attrib.py
pyfolio/plotting.py
pyfolio/pos.py
pyfolio/risk.py
pyfolio/round_trips.py
pyfolio/tears.py
pyfolio/timeseries.py
pyfolio/txn.py
pyfolio/utils.py
pyfolio.egg-info/PKG-INFO
pyfolio.egg-info/SOURCES.txt
pyfolio.egg-info/dependency_links.txt
pyfolio.egg-info/pbr.json
pyfolio.egg-info/requires.txt
pyfolio.egg-info/top_level.txt
pyfolio/tests/__init__.py
pyfolio/tests/test_capacity.py
pyfolio/tests/test_nbs.py
pyfolio/tests/test_perf_attrib.py
pyfolio/tests/test_pos.py
pyfolio/tests/test_risk.py
pyfolio/tests/test_round_trips.py
pyfolio/tests/test_tears.py
pyfolio/tests/test_timeseries.py
pyfolio/tests/test_txn.py